content_based/__init__.py
content_based/content_based.py
content_based/content_based_orm.py
contentbased_recommend-0.1.0.dist-info/WHEEL
contentbased_recommend-0.1.0.dist-info/METADATA
contentbased_recommend-0.1.0.dist-info/RECORD
