Metadata-Version: 2.1
Name: contentbased-recommend
Version: 0.1.0
Summary: 
Author: Crparichaya
Author-email: parichaya.yan@ku.th
Requires-Python: >=3.12,<4.0
Classifier: Programming Language :: Python :: 3
Requires-Dist: SQLAlchemy (>=2.0.31,<3.0.0)
Requires-Dist: pyodbc (>=5.1.0,<6.0.0)
Requires-Dist: python-dotenv (>=1.0.1,<2.0.0)
Requires-Dist: torch (>=2.4.0,<3.0.0)
